fiopy/__init__.py
fiopy/config.py
fiopy/fio.py
fiopy/annotations/__init__.py
fiopy/annotations/autowire.py
fiopy/config/api.yaml
fiopy/enums/__init__.py
fiopy/enums/account_role.py
fiopy/enums/base.py
fiopy/enums/config_type.py
fiopy/enums/session_method.py
fiopy/enums/team_role.py
fiopy/enums/user_role.py
fiopy/exceptions/__init__.py
fiopy/exceptions/rate_limited.py
fiopy/http/__init__.py
fiopy/http/http_request.py
fiopy/http/http_response.py
fiopy/http/rate_limit.py
fiopy/http/enums/__init__.py
fiopy/http/enums/http_request_method.py
fiopy/models/__init__.py
fiopy/models/account.py
fiopy/models/asset.py
fiopy/models/asset_impression.py
fiopy/models/base.py
fiopy/models/base_asset.py
fiopy/models/base_container.py
fiopy/models/base_folder.py
fiopy/models/comment.py
fiopy/models/encoder.py
fiopy/models/plan.py
fiopy/models/plan_features.py
fiopy/models/project.py
fiopy/models/project_prefs.py
fiopy/models/project_root_folder.py
fiopy/models/project_settings.py
fiopy/models/project_user_prefs.py
fiopy/models/promotion.py
fiopy/models/review_link.py
fiopy/models/review_link_item.py
fiopy/models/subscription.py
fiopy/models/team.py
fiopy/models/user.py
fiopyhelper-0.0.2.dist-info/METADATA
fiopyhelper-0.0.2.dist-info/WHEEL
fiopyhelper-0.0.2.dist-info/top_level.txt
fiopyhelper-0.0.2.dist-info/RECORD
